LICENSE
README.md
setup.cfg
setup.py
pyoptmat/__init__.py
pyoptmat/chunktime.py
pyoptmat/damage.py
pyoptmat/experiments.py
pyoptmat/flowrules.py
pyoptmat/hardening.py
pyoptmat/models.py
pyoptmat/neuralode.py
pyoptmat/ode.py
pyoptmat/optimize.py
pyoptmat/scaling.py
pyoptmat/solvers.py
pyoptmat/temperature.py
pyoptmat/utility.py
pyoptmat.egg-info/PKG-INFO
pyoptmat.egg-info/SOURCES.txt
pyoptmat.egg-info/dependency_links.txt
pyoptmat.egg-info/requires.txt
pyoptmat.egg-info/top_level.txt
pyoptmat.egg-info/zip-safe
test/test_adjoint_gradients.py
test/test_batch_gradient.py
test/test_chunktime.py
test/test_damage.py
test/test_flowrules.py
test/test_hardening.py
test/test_ic_gradient.py
test/test_model_gradient.py
test/test_models.py
test/test_ode.py
test/test_scaling.py
test/test_solvers.py
test/test_temperature_scaling.py
test/test_utility.py