Metadata-Version: 2.1
Name: pyoptmat
Version: 1.3.4
Summary: Statistical inference for material models
Home-page: https://github.com/Argonne-National-Laboratory/pyoptmat
Author: Argonne National Laboratory
Author-email: messner@anl.gov
License: UNKNOWN
Keywords: materials inference modeling
Platform: UNKNOWN
Classifier: Intended Audience :: Science/Research
Classifier: License :: OSI Approved :: MIT License
Classifier: Programming Language :: Python :: 3
Classifier: Operating System :: OS Independent
Requires-Python: >=3.6
License-File: LICENSE
